{
  "finalRunId": "7b857074-2fb9-42f9-b676-8cfcee42a44f",
  "route": "/client/project/$id?tab=stages",
  "fixtureProjectId": "3222a8a0-5ad3-4b1f-96ef-ac11d3b8203d",
  "fixtureAcceptanceId": "ad8ee32e-0eb3-4763-b323-3ea774547760",
  "component": "AcceptanceDialog",
  "focusableCount": 3,
  "checks": {
    "triggerFound": false,
    "dialogOpened": true,
    "roleDialog": true,
    "ariaModalTrue": true,
    "accessibleNamePresent": true,
    "initialFocusInsideDialog": true,
    "tabHeldInside": true,
    "shiftTabHeldInside": true,
    "escapeClosed": true,
    "focusReturnedToTrigger": true,
    "shortCommentAccessibleError": true,
    "submitDisabledDuringRequest": true,
    "secondRequestNotSent": true,
    "resolvedAcceptanceCannotResolveAgain": true
  },
  "passed": false
}